Log/__init__.py
Log/developmentLog.py
PyQtGuiLib/__init__.py
PyQtGuiLib/animation/PropertyAnimation.py
PyQtGuiLib/animation/__init__.py
PyQtGuiLib/animation/animation.py
PyQtGuiLib/core/__init__.py
PyQtGuiLib/core/bubbleWidget.py
PyQtGuiLib/core/flowLayout.py
PyQtGuiLib/core/listWidget.py
PyQtGuiLib/core/pullOver.py
PyQtGuiLib/core/rollWidget.py
PyQtGuiLib/core/slideShow.py
PyQtGuiLib/core/toolBox.py
PyQtGuiLib/core/toolList.py
PyQtGuiLib/core/charRooms/__init__.py
PyQtGuiLib/core/charRooms/chatRoom.py
PyQtGuiLib/core/charRooms/headImage.py
PyQtGuiLib/core/charRooms/message.py
PyQtGuiLib/core/charRooms/test.py
PyQtGuiLib/core/charRooms/transmitter.py
PyQtGuiLib/core/charRooms/utility.py
PyQtGuiLib/core/comboBox/__init__.py
PyQtGuiLib/core/comboBox/comboBox.py
PyQtGuiLib/core/comboBox/comboCheckBox/__init__.py
PyQtGuiLib/core/comboBox/comboCheckBox/comboCheckBox.py
PyQtGuiLib/core/comboBox/comboCheckBox/py_message_box.py
PyQtGuiLib/core/comboBox/comboCheckBox/py_style.py
PyQtGuiLib/core/drawers/__init__.py
PyQtGuiLib/core/drawers/drawer.py
PyQtGuiLib/core/logBrowser/__init__.py
PyQtGuiLib/core/logBrowser/loadLogTh.py
PyQtGuiLib/core/logBrowser/logBrowser.py
PyQtGuiLib/core/logBrowser/logSizeTh.py
PyQtGuiLib/core/notice/__init__.py
PyQtGuiLib/core/notice/notice.py
PyQtGuiLib/core/pager/__init__.py
PyQtGuiLib/core/pager/pageCuttingButtonGroup.py
PyQtGuiLib/core/palettes/__init__.py
PyQtGuiLib/core/palettes/colorHsv.py
PyQtGuiLib/core/palettes/paletteFrame.py
PyQtGuiLib/core/palettes/palettetools.py
PyQtGuiLib/core/palettes/paletteTools/__init__.py
PyQtGuiLib/core/palettes/paletteTools/area.py
PyQtGuiLib/core/palettes/paletteTools/paletteToolUI.py
PyQtGuiLib/core/palettes/paletteTools/palettetools.py
PyQtGuiLib/core/progressBar/__init__.py
PyQtGuiLib/core/progressBar/circularBar.py
PyQtGuiLib/core/progressBar/circularProgressBar.py
PyQtGuiLib/core/progressBar/gradientBar.py
PyQtGuiLib/core/progressBar/loadBar.py
PyQtGuiLib/core/progressBar/waterBar.py
PyQtGuiLib-2.8.25.1.dist-info/LICENSE.txt
PyQtGuiLib-2.8.25.1.dist-info/METADATA
PyQtGuiLib-2.8.25.1.dist-info/WHEEL
PyQtGuiLib-2.8.25.1.dist-info/top_level.txt
PyQtGuiLib-2.8.25.1.dist-info/RECORD
