Metadata-Version: 2.1
Name: PyQtGuiLib
Version: 2.8.25.1
Summary: Python version of the qt component library.
Home-page: https://github.com/LX-sys/PyQtGuiLib
Author: LX
Author-email: lx984608061@163.com
Classifier: Programming Language :: Python :: 3
Classifier: License :: OSI Approved :: MIT License
Classifier: Operating System :: OS Independent
License-File: LICENSE.txt
